premaidai_gym/__init__.py
premaidai_gym/assets/LICENSE
premaidai_gym/assets/meshes/LICENSE.txt
premaidai_gym/assets/meshes/body.dae
premaidai_gym/assets/meshes/head.dae
premaidai_gym/assets/meshes/l_ankle.dae
premaidai_gym/assets/meshes/l_foot.dae
premaidai_gym/assets/meshes/l_hand.dae
premaidai_gym/assets/meshes/l_hip_joint.dae
premaidai_gym/assets/meshes/l_larm.dae
premaidai_gym/assets/meshes/l_larm_joint.dae
premaidai_gym/assets/meshes/l_lleg.dae
premaidai_gym/assets/meshes/l_uarm.dae
premaidai_gym/assets/meshes/l_uarm_joint.dae
premaidai_gym/assets/meshes/l_uleg.dae
premaidai_gym/assets/meshes/l_uleg_root.dae
premaidai_gym/assets/meshes/neck.dae
premaidai_gym/assets/meshes/neck_pitch.dae
premaidai_gym/assets/meshes/neck_yaw.dae
premaidai_gym/assets/meshes/r_ankle.dae
premaidai_gym/assets/meshes/r_foot.dae
premaidai_gym/assets/meshes/r_hand.dae
premaidai_gym/assets/meshes/r_hip_joint.dae
premaidai_gym/assets/meshes/r_larm.dae
premaidai_gym/assets/meshes/r_larm_joint.dae
premaidai_gym/assets/meshes/r_lleg.dae
premaidai_gym/assets/meshes/r_uarm.dae
premaidai_gym/assets/meshes/r_uarm_joint.dae
premaidai_gym/assets/meshes/r_uleg.dae
premaidai_gym/assets/meshes/r_uleg_root.dae
premaidai_gym/assets/premaidai.urdf
premaidai_gym/roboschool_premaidai_walker.py
premaidai_gym/simple_walk_controller.py
premaidai_gym-1.1.0.dist-info/WHEEL
premaidai_gym-1.1.0.dist-info/METADATA
premaidai_gym-1.1.0.dist-info/RECORD
